{
	"info": {
		"_postman_id": "f730727a-4819-4c1a-9b79-3fa29b4c3758",
		"name": "ASTUDIO laravel",
		"schema": "https://schema.getpostman.com/json/collection/v2.1.0/collection.json",
		"_exporter_id": "4217142"
	},
	"item": [
		{
			"name": "Auth",
			"item": [
				{
					"name": "Register",
					"request": {
						"method": "POST",
						"header": [
							{
								"key": "Accept",
								"value": "application/json",
								"type": "text"
							}
						],
						"body": {
							"mode": "raw",
							"raw": "{\n    \"first_name\": \"Test\",\n    \"last_name\":\"User\",\n    \"date_of_birth\":\"1990-11-03\",\n    \"gender\":\"male\",\n    \"email\":\"testuser@gmail.com\",\n    \"password\":\"password\",\n    \"password_confirmation\":\"password\"\n}",
							"options": {
								"raw": {
									"language": "json"
								}
							}
						},
						"url": {
							"raw": "http://127.0.0.1:8000/api/register",
							"protocol": "http",
							"host": [
								"127",
								"0",
								"0",
								"1"
							],
							"port": "8000",
							"path": [
								"api",
								"register"
							]
						}
					},
					"response": []
				},
				{
					"name": "Login",
					"request": {
						"method": "POST",
						"header": [
							{
								"key": "Accept",
								"value": "application/json",
								"type": "text"
							}
						],
						"body": {
							"mode": "raw",
							"raw": "{\n    \"email\":\"testuser@gmail.com\",\n    \"password\":\"password\"\n}",
							"options": {
								"raw": {
									"language": "json"
								}
							}
						},
						"url": {
							"raw": "http://127.0.0.1:8000/api/login",
							"protocol": "http",
							"host": [
								"127",
								"0",
								"0",
								"1"
							],
							"port": "8000",
							"path": [
								"api",
								"login"
							]
						}
					},
					"response": []
				},
				{
					"name": "Logout",
					"request": {
						"method": "POST",
						"header": [
							{
								"key": "Accept",
								"value": "application/json",
								"type": "text"
							},
							{
								"key": "Authorization",
								"value": "Bearer {{token}}",
								"type": "text"
							}
						],
						"body": {
							"mode": "raw",
							"raw": "",
							"options": {
								"raw": {
									"language": "json"
								}
							}
						},
						"url": {
							"raw": "http://127.0.0.1:8000/api/logout",
							"protocol": "http",
							"host": [
								"127",
								"0",
								"0",
								"1"
							],
							"port": "8000",
							"path": [
								"api",
								"logout"
							]
						}
					},
					"response": []
				}
			]
		},
		{
			"name": "User",
			"item": [
				{
					"name": "Read All Users",
					"request": {
						"method": "GET",
						"header": [
							{
								"key": "Accept",
								"value": "application/json",
								"type": "text"
							},
							{
								"key": "Authorization",
								"value": "Bearer {{token}}",
								"type": "text"
							}
						],
						"url": {
							"raw": "http://127.0.0.1:8000/api/users?first_name=Renuka&gender=female&date_of_birth=1991-11-03",
							"protocol": "http",
							"host": [
								"127",
								"0",
								"0",
								"1"
							],
							"port": "8000",
							"path": [
								"api",
								"users"
							],
							"query": [
								{
									"key": "first_name",
									"value": "Renuka"
								},
								{
									"key": "gender",
									"value": "female"
								},
								{
									"key": "date_of_birth",
									"value": "1991-11-03"
								}
							]
						}
					},
					"response": []
				},
				{
					"name": "Read a User",
					"request": {
						"method": "GET",
						"header": [
							{
								"key": "Accept",
								"value": "application/json",
								"type": "text"
							},
							{
								"key": "Authorization",
								"value": "Bearer {{token}}",
								"type": "text"
							}
						],
						"url": {
							"raw": "http://127.0.0.1:8000/api/users/1",
							"protocol": "http",
							"host": [
								"127",
								"0",
								"0",
								"1"
							],
							"port": "8000",
							"path": [
								"api",
								"users",
								"1"
							],
							"query": [
								{
									"key": "",
									"value": "",
									"disabled": true
								}
							]
						}
					},
					"response": []
				},
				{
					"name": "Create a User",
					"request": {
						"method": "POST",
						"header": [
							{
								"key": "Accept",
								"value": "application/json",
								"type": "text"
							},
							{
								"key": "Authorization",
								"value": "Bearer {{token}}",
								"type": "text"
							}
						],
						"body": {
							"mode": "raw",
							"raw": "{\n    \"first_name\": \"Renuka\",\n    \"last_name\":\"Pahade\",\n    \"date_of_birth\":\"1991-11-03\",\n    \"gender\":\"female\",\n    \"email\":\"renuka396@gmail.com\",\n    \"password\":\"password\",\n    \"password_confirmation\":\"password\"\n}",
							"options": {
								"raw": {
									"language": "json"
								}
							}
						},
						"url": {
							"raw": "http://127.0.0.1:8000/api/users",
							"protocol": "http",
							"host": [
								"127",
								"0",
								"0",
								"1"
							],
							"port": "8000",
							"path": [
								"api",
								"users"
							],
							"query": [
								{
									"key": "",
									"value": "",
									"disabled": true
								}
							]
						}
					},
					"response": []
				},
				{
					"name": "Update a User",
					"request": {
						"method": "POST",
						"header": [
							{
								"key": "Accept",
								"value": "application/json",
								"type": "text"
							},
							{
								"key": "Authorization",
								"value": "Bearer {{token}}",
								"type": "text"
							}
						],
						"body": {
							"mode": "raw",
							"raw": "{\n    \"id\": 2,\n    \"first_name\": \"Renuka\",\n    \"last_name\":\"P\",\n    \"date_of_birth\":\"1991-11-04\",\n    \"gender\":\"female\",\n    \"email\":\"renuka3933@gmail.com\",\n    \"password\":\"password2\",\n    \"password_confirmation\":\"password2\"\n}",
							"options": {
								"raw": {
									"language": "json"
								}
							}
						},
						"url": {
							"raw": "http://127.0.0.1:8000/api/users/update",
							"protocol": "http",
							"host": [
								"127",
								"0",
								"0",
								"1"
							],
							"port": "8000",
							"path": [
								"api",
								"users",
								"update"
							],
							"query": [
								{
									"key": "",
									"value": "",
									"disabled": true
								}
							]
						}
					},
					"response": []
				},
				{
					"name": "Delete a User",
					"request": {
						"method": "POST",
						"header": [
							{
								"key": "Accept",
								"value": "application/json",
								"type": "text"
							},
							{
								"key": "Authorization",
								"value": "Bearer {{token}}",
								"type": "text"
							}
						],
						"body": {
							"mode": "raw",
							"raw": "{\n    \"id\": 5\n}",
							"options": {
								"raw": {
									"language": "json"
								}
							}
						},
						"url": {
							"raw": "http://127.0.0.1:8000/api/users/delete",
							"protocol": "http",
							"host": [
								"127",
								"0",
								"0",
								"1"
							],
							"port": "8000",
							"path": [
								"api",
								"users",
								"delete"
							],
							"query": [
								{
									"key": "",
									"value": "",
									"disabled": true
								}
							]
						}
					},
					"response": []
				}
			],
			"event": [
				{
					"listen": "prerequest",
					"script": {
						"type": "text/javascript",
						"packages": {},
						"exec": [
							""
						]
					}
				},
				{
					"listen": "test",
					"script": {
						"type": "text/javascript",
						"packages": {},
						"exec": [
							""
						]
					}
				}
			]
		},
		{
			"name": "Project",
			"item": [
				{
					"name": "Read All Projects",
					"request": {
						"method": "GET",
						"header": [
							{
								"key": "Accept",
								"value": "application/json",
								"type": "text"
							},
							{
								"key": "Authorization",
								"value": "Bearer {{token}}",
								"type": "text"
							}
						],
						"url": {
							"raw": "http://127.0.0.1:8000/api/projects?name=Project%20Beta&status=completed&department=Design",
							"protocol": "http",
							"host": [
								"127",
								"0",
								"0",
								"1"
							],
							"port": "8000",
							"path": [
								"api",
								"projects"
							],
							"query": [
								{
									"key": "name",
									"value": "Project%20Beta"
								},
								{
									"key": "status",
									"value": "completed"
								},
								{
									"key": "department",
									"value": "Design"
								}
							]
						}
					},
					"response": []
				},
				{
					"name": "Read a Project",
					"request": {
						"method": "GET",
						"header": [
							{
								"key": "Accept",
								"value": "application/json",
								"type": "text"
							},
							{
								"key": "Authorization",
								"value": "Bearer {{token}}",
								"type": "text"
							}
						],
						"url": {
							"raw": "http://127.0.0.1:8000/api/projects/1",
							"protocol": "http",
							"host": [
								"127",
								"0",
								"0",
								"1"
							],
							"port": "8000",
							"path": [
								"api",
								"projects",
								"1"
							],
							"query": [
								{
									"key": "",
									"value": "",
									"disabled": true
								}
							]
						}
					},
					"response": []
				},
				{
					"name": "Create a Project",
					"request": {
						"method": "POST",
						"header": [
							{
								"key": "Accept",
								"value": "application/json",
								"type": "text"
							},
							{
								"key": "Authorization",
								"value": "Bearer {{token}}",
								"type": "text"
							}
						],
						"body": {
							"mode": "raw",
							"raw": "{\n    \"name\": \"Project MVP\",\n    \"department\": \"Manufacturing\",\n    \"start_date\": \"2024-03-01\",\n    \"end_date\": \"2024-11-01\",\n    \"status\": \"ongoing\"\n}",
							"options": {
								"raw": {
									"language": "json"
								}
							}
						},
						"url": {
							"raw": "http://127.0.0.1:8000/api/projects",
							"protocol": "http",
							"host": [
								"127",
								"0",
								"0",
								"1"
							],
							"port": "8000",
							"path": [
								"api",
								"projects"
							],
							"query": [
								{
									"key": "",
									"value": "",
									"disabled": true
								}
							]
						}
					},
					"response": []
				},
				{
					"name": "Update a Project",
					"request": {
						"method": "POST",
						"header": [
							{
								"key": "Accept",
								"value": "application/json",
								"type": "text"
							},
							{
								"key": "Authorization",
								"value": "Bearer {{token}}",
								"type": "text"
							}
						],
						"body": {
							"mode": "raw",
							"raw": "{\n    \"id\": 2,\n    \"name\": \"Project Alpha Updated\",\n    \"department\": \"Engineering\",\n    \"start_date\": \"2024-01-01\",\n    \"end_date\": \"2024-12-31\",\n    \"status\": \"completed\"\n}",
							"options": {
								"raw": {
									"language": "json"
								}
							}
						},
						"url": {
							"raw": "http://127.0.0.1:8000/api/projects/update",
							"protocol": "http",
							"host": [
								"127",
								"0",
								"0",
								"1"
							],
							"port": "8000",
							"path": [
								"api",
								"projects",
								"update"
							],
							"query": [
								{
									"key": "",
									"value": "",
									"disabled": true
								}
							]
						}
					},
					"response": []
				},
				{
					"name": "Delete a Project",
					"request": {
						"method": "POST",
						"header": [
							{
								"key": "Accept",
								"value": "application/json",
								"type": "text"
							},
							{
								"key": "Authorization",
								"value": "Bearer {{token}}",
								"type": "text"
							}
						],
						"body": {
							"mode": "raw",
							"raw": "{\n    \"id\": 2\n}",
							"options": {
								"raw": {
									"language": "json"
								}
							}
						},
						"url": {
							"raw": "http://127.0.0.1:8000/api/projects/delete",
							"protocol": "http",
							"host": [
								"127",
								"0",
								"0",
								"1"
							],
							"port": "8000",
							"path": [
								"api",
								"projects",
								"delete"
							],
							"query": [
								{
									"key": "",
									"value": "",
									"disabled": true
								}
							]
						}
					},
					"response": []
				}
			],
			"event": [
				{
					"listen": "prerequest",
					"script": {
						"type": "text/javascript",
						"packages": {},
						"exec": [
							""
						]
					}
				},
				{
					"listen": "test",
					"script": {
						"type": "text/javascript",
						"packages": {},
						"exec": [
							""
						]
					}
				}
			]
		},
		{
			"name": "Timesheet",
			"item": [
				{
					"name": "Read All Timesheets",
					"request": {
						"method": "GET",
						"header": [
							{
								"key": "Accept",
								"value": "application/json",
								"type": "text"
							},
							{
								"key": "Authorization",
								"value": "Bearer {{token}}",
								"type": "text"
							}
						],
						"url": {
							"raw": "http://127.0.0.1:8000/api/timesheets?task_name=Development%20Task%201&user_id=2&project_id=1&date=2024-09-20",
							"protocol": "http",
							"host": [
								"127",
								"0",
								"0",
								"1"
							],
							"port": "8000",
							"path": [
								"api",
								"timesheets"
							],
							"query": [
								{
									"key": "task_name",
									"value": "Development%20Task%201"
								},
								{
									"key": "user_id",
									"value": "2"
								},
								{
									"key": "project_id",
									"value": "1"
								},
								{
									"key": "date",
									"value": "2024-09-20"
								}
							]
						}
					},
					"response": []
				},
				{
					"name": "Read a Timesheet",
					"request": {
						"method": "GET",
						"header": [
							{
								"key": "Accept",
								"value": "application/json",
								"type": "text"
							},
							{
								"key": "Authorization",
								"value": "Bearer {{token}}",
								"type": "text"
							}
						],
						"url": {
							"raw": "http://127.0.0.1:8000/api/timesheets/1",
							"protocol": "http",
							"host": [
								"127",
								"0",
								"0",
								"1"
							],
							"port": "8000",
							"path": [
								"api",
								"timesheets",
								"1"
							],
							"query": [
								{
									"key": "",
									"value": "",
									"disabled": true
								}
							]
						}
					},
					"response": []
				},
				{
					"name": "Create a Timesheet",
					"request": {
						"method": "POST",
						"header": [
							{
								"key": "Accept",
								"value": "application/json",
								"type": "text"
							},
							{
								"key": "Authorization",
								"value": "Bearer {{token}}",
								"type": "text"
							}
						],
						"body": {
							"mode": "raw",
							"raw": "{\n    \"task_name\": \"Development Task 4\",\n    \"date\": \"2024-09-24\",\n    \"hours\": 8,\n    \"user_id\": 3,\n    \"project_id\": 3\n}",
							"options": {
								"raw": {
									"language": "json"
								}
							}
						},
						"url": {
							"raw": "http://127.0.0.1:8000/api/timesheets",
							"protocol": "http",
							"host": [
								"127",
								"0",
								"0",
								"1"
							],
							"port": "8000",
							"path": [
								"api",
								"timesheets"
							],
							"query": [
								{
									"key": "",
									"value": "",
									"disabled": true
								}
							]
						}
					},
					"response": []
				},
				{
					"name": "Update a Timesheet",
					"request": {
						"method": "POST",
						"header": [
							{
								"key": "Accept",
								"value": "application/json",
								"type": "text"
							},
							{
								"key": "Authorization",
								"value": "Bearer {{token}}",
								"type": "text"
							}
						],
						"body": {
							"mode": "raw",
							"raw": "{\n    \"id\": 1,\n    \"task_name\": \"Development Task 1 Updated\",\n    \"date\": \"2024-09-21\",\n    \"hours\": 7,\n    \"user_id\": 1,\n    \"project_id\": 3\n}",
							"options": {
								"raw": {
									"language": "json"
								}
							}
						},
						"url": {
							"raw": "http://127.0.0.1:8000/api/timesheets/update",
							"protocol": "http",
							"host": [
								"127",
								"0",
								"0",
								"1"
							],
							"port": "8000",
							"path": [
								"api",
								"timesheets",
								"update"
							],
							"query": [
								{
									"key": "",
									"value": "",
									"disabled": true
								}
							]
						}
					},
					"response": []
				},
				{
					"name": "Delete a Timesheet",
					"request": {
						"method": "POST",
						"header": [
							{
								"key": "Accept",
								"value": "application/json",
								"type": "text"
							},
							{
								"key": "Authorization",
								"value": "Bearer {{token}}",
								"type": "text"
							}
						],
						"body": {
							"mode": "raw",
							"raw": "{\n    \"id\": 1\n}",
							"options": {
								"raw": {
									"language": "json"
								}
							}
						},
						"url": {
							"raw": "http://127.0.0.1:8000/api/timesheets/delete",
							"protocol": "http",
							"host": [
								"127",
								"0",
								"0",
								"1"
							],
							"port": "8000",
							"path": [
								"api",
								"timesheets",
								"delete"
							],
							"query": [
								{
									"key": "",
									"value": "",
									"disabled": true
								}
							]
						}
					},
					"response": []
				}
			],
			"event": [
				{
					"listen": "prerequest",
					"script": {
						"type": "text/javascript",
						"packages": {},
						"exec": [
							""
						]
					}
				},
				{
					"listen": "test",
					"script": {
						"type": "text/javascript",
						"packages": {},
						"exec": [
							""
						]
					}
				}
			]
		}
	],
	"event": [
		{
			"listen": "prerequest",
			"script": {
				"type": "text/javascript",
				"packages": {},
				"exec": [
					""
				]
			}
		},
		{
			"listen": "test",
			"script": {
				"type": "text/javascript",
				"packages": {},
				"exec": [
					""
				]
			}
		}
	],
	"variable": [
		{
			"key": "token",
			"value": "1|aRhxJf3XVANO55npMKCCOIqZx6YTRamL1ObIzKqlb931f69b"
		}
	]
}